hedgebuddy/__init__.py
hedgebuddy/core.py
hedgebuddy/exceptions.py
hedgebuddy-0.5.1.dist-info/licenses/LICENSE
hedgebuddy-0.5.1.dist-info/METADATA
hedgebuddy-0.5.1.dist-info/WHEEL
hedgebuddy-0.5.1.dist-info/top_level.txt
hedgebuddy-0.5.1.dist-info/RECORD
