Metadata-Version: 2.4
Name: hedgebuddy
Version: 0.5.1
Summary: Cross-platform environment variable management for Python scripts without system pollution
Author-email: Shaked Lipszyc <shakedl@gmail.com>
License: MIT
Project-URL: Homepage, https://github.com/shakedex/hedgebuddy
Project-URL: Repository, https://github.com/shakedex/hedgebuddy
Project-URL: Issues, https://github.com/shakedex/hedgebuddy/issues
Keywords: environment,variables,configuration,cross-platform,hedge,filmmaking
Classifier: Development Status :: 4 - Beta
Classifier: Intended Audience :: Developers
Classifier: Intended Audience :: End Users/Desktop
Classifier: License :: OSI Approved :: MIT License
Classifier: Programming Language :: Python :: 3
Classifier: Programming Language :: Python :: 3.13
Classifier: Operating System :: Microsoft :: Windows
Classifier: Operating System :: MacOS
Classifier: Topic :: Software Development :: Libraries :: Python Modules
Classifier: Topic :: Multimedia :: Video
Requires-Python: >=3.13
License-File: LICENSE
Provides-Extra: dev
Requires-Dist: pytest>=8.0.0; extra == "dev"
Requires-Dist: pytest-cov>=4.1.0; extra == "dev"
Dynamic: license-file
